tinsel/__init__.py
tinsel/lib.py
tinsel/types.py
tinsel-0.3.0.dist-info/METADATA
tinsel-0.3.0.dist-info/RECORD
tinsel-0.3.0.dist-info/WHEEL
tinsel-0.3.0.dist-info/top_level.txt
