Metadata-Version: 2.1
Name: tinsel
Version: 0.3.0
Summary: PySpark schema generator
Home-page: https://github.com/Orhideous/tinsel
Author: Andriy Kushnir (Orhideous)
Author-email: me@orhideous.name
License: MIT license
Keywords: tinsel,pyspark,spark,schema,struct
Platform: UNKNOWN
Classifier: Development Status :: 4 - Beta
Classifier: Intended Audience :: Developers
Classifier: License :: OSI Approved :: MIT License
Classifier: Natural Language :: English
Classifier: Programming Language :: Python :: 3.6
Classifier: Programming Language :: Python :: 3.7
Requires-Dist: pyspark (>=2.3)
